pygrocy/__init__.py
pygrocy/base.py
pygrocy/grocy.py
pygrocy/grocy_api_client.py
pygrocy/utils.py
pygrocy/data_models/__init__.py
pygrocy/data_models/battery.py
pygrocy/data_models/chore.py
pygrocy/data_models/generic.py
pygrocy/data_models/meal_items.py
pygrocy/data_models/product.py
pygrocy/data_models/system.py
pygrocy/data_models/task.py
pygrocy/data_models/user.py
pygrocy/errors/__init__.py
pygrocy/errors/grocy_error.py
test/__init__.py
test/conftest.py
test/test_battery.py
test/test_chores.py
test/test_const.py
test/test_generic.py
test/test_grocy.py
test/test_grocy_api_client.py
test/test_meal_plan.py
test/test_meal_plan_sections.py
test/test_misc.py
test/test_product.py
test/test_product_groups.py
test/test_shoppinglist.py
test/test_stock.py
test/test_system.py
test/test_tasks.py
test/test_users.py
test/test_utils.py
pygrocy-2.1.0.dist-info/LICENSE
pygrocy-2.1.0.dist-info/METADATA
pygrocy-2.1.0.dist-info/WHEEL
pygrocy-2.1.0.dist-info/top_level.txt
pygrocy-2.1.0.dist-info/RECORD
