Metadata-Version: 2.1
Name: pygrocy
Version: 2.1.0
Home-page: https://github.com/sebrut/pygrocy
Author: Sebastian Rutofski
Author-email: kontakt@sebastian-rutofski.de
License: MIT
Classifier: Programming Language :: Python :: 3
Classifier: License :: OSI Approved :: MIT License
Classifier: Operating System :: OS Independent
License-File: LICENSE
Requires-Dist: requests
Requires-Dist: deprecation ~=2.1.0
Requires-Dist: pydantic <1.11.0,>=1.8.2
Requires-Dist: backports.zoneinfo ; python_version < "3.9"
